{
    "packingMode": "random",
    "partners_position": [],
    "weight": 0.20000000000000001,
    "color": [0.419555953733, 0.225881043678, 0.223898161324],
    "results": [],
    "radii": [[10.0, 10.0, 10.0, 10.0, 10.0, 10.0, 10.0, 10.0]],
    "cutoff_boundary": null,
    "encapsulatingRadius": 42.3939525705,
    "positions2": null,
    "rejectionThreshold": 30,
    "isAttractor": false,
    "Type": "MultiSphere",
    "orientBiasRotRangeMax": -3.1415926535897931,
    "gradient": "",
    "nbMol": 0,
    "jitterMax": [1.0, 1.0, 1.0],
    "packingPriority": 0,
    "rotAxis": [
        0.0,
        0.0,
        0.0
    ],
    "overwrite_nbMol_value": 0,
    "nbJitter": 5,
    "molarity": 0,
    "useOrientBias": false,
    "rotRange": 6.2831000000000001,
    "coordsystem": "left",
    "meshFile": "ghrB_coarse.dae",
    "orientBiasRotRangeMin": -3.1415926535897931,
    "perturbAxisAmplitude": 0.10000000000000001,
    "proba_binding": 0.5,
    "principalVector": [1.0, 0.0, 0.0],
    "offset": [0.0, 0.0, 0.0],
    "properties": {},
    "partners_name": [],
    "name": "ghrB",
    "positions": [
        [[2.400443271166902, 6.632616895451174, 0.21320316459596983], [-9.679242464749402, 21.77469167838406, -4.077356158654116], [16.35520802567206, -10.19908158526635, 0.3466083770288702], [-16.731336223659106, 6.808678428244582, -9.174978075974002], [-17.3343817255118, 11.408998444293024, 5.806354182487025], [17.36440438176631, -10.882150747290455, 22.05889465616041], [-0.08697620889129913, -13.689074835412601, 5.331576699244331], [10.021605100016021, -6.296711736404741, -12.945322076716863]]
    ],
    "meshName": "ghrB",
    "excluded_partners_name": [],
    "placeType": "jitter",
    "cutoff_surface": 20.052597999572754,
    "proba_not_binding": 0.5,
    "source": {
        "pdb": "b3553_1_322_5aow_clean",
        "transform": {
            "center": true
        }
    },
    "use_mesh_rb": false,
    "pdb": "b3553_1_322_5aow_clean",
    "useRotAxis": 0
}