{
    "packingMode": "random",
    "partners_position": [],
    "weight": 0.20000000000000001,
    "color": [0.659136910275, 0.804477503045, 0.759047502081],
    "results": [],
    "radii": [[10.0, 10.0, 10.0, 10.0, 10.0]],
    "cutoff_boundary": null,
    "encapsulatingRadius": 33.6609179134,
    "positions2": null,
    "rejectionThreshold": 30,
    "isAttractor": false,
    "Type": "MultiSphere",
    "orientBiasRotRangeMax": -3.1415926535897931,
    "gradient": "",
    "nbMol": 0,
    "jitterMax": [1.0, 1.0, 1.0],
    "packingPriority": 0,
    "rotAxis": [
        0.0,
        0.0,
        0.0
    ],
    "overwrite_nbMol_value": 0,
    "nbJitter": 5,
    "molarity": 0,
    "useOrientBias": false,
    "rotRange": 6.2831000000000001,
    "coordsystem": "left",
    "meshFile": "kdsC_coarse.dae",
    "orientBiasRotRangeMin": -3.1415926535897931,
    "perturbAxisAmplitude": 0.10000000000000001,
    "proba_binding": 0.5,
    "principalVector": [1.0, 0.0, 0.0],
    "offset": [0.0, 0.0, 0.0],
    "properties": {},
    "partners_name": [],
    "name": "kdsC",
    "positions": [
        [[-7.8900077171653455, 11.05927406438049, -2.1449865600400897], [4.894151732412887, 7.969114243692353, 5.506159671267434], [13.776507282197667, -7.76559189190751, -0.6046552426721098], [-3.1181885549318547, -3.0588031423190736, -9.568116402431748], [-6.328110011037283, -6.867292606396437, 6.071928845197097]]
    ],
    "meshName": "kdsC",
    "excluded_partners_name": [],
    "placeType": "jitter",
    "cutoff_surface": 20.052597999572754,
    "proba_not_binding": 0.5,
    "source": {
        "pdb": "3hyc-A_clean",
        "transform": {
            "center": true
        }
    },
    "use_mesh_rb": false,
    "pdb": "3hyc-A_clean",
    "useRotAxis": 0
}