{
    "packingMode": "random",
    "partners_position": [],
    "weight": 0.20000000000000001,
    "color": [0.124450684336, 0.281968003015, 0.983211348866],
    "results": [],
    "radii": [[10.0, 10.0, 10.0, 10.0, 10.0, 10.0, 10.0, 10.0, 10.0]],
    "cutoff_boundary": null,
    "encapsulatingRadius": 36.3362275097,
    "positions2": null,
    "rejectionThreshold": 30,
    "isAttractor": false,
    "Type": "MultiSphere",
    "orientBiasRotRangeMax": -3.1415926535897931,
    "gradient": "",
    "nbMol": 0,
    "jitterMax": [1.0, 1.0, 1.0],
    "packingPriority": 0,
    "rotAxis": [
        0.0,
        0.0,
        0.0
    ],
    "overwrite_nbMol_value": 0,
    "nbJitter": 5,
    "molarity": 0,
    "useOrientBias": false,
    "rotRange": 6.2831000000000001,
    "coordsystem": "left",
    "meshFile": "rfaB_coarse.dae",
    "orientBiasRotRangeMin": -3.1415926535897931,
    "perturbAxisAmplitude": 0.10000000000000001,
    "proba_binding": 0.5,
    "principalVector": [1.0, 0.0, 0.0],
    "offset": [0.0, 0.0, 0.0],
    "properties": {},
    "partners_name": [],
    "name": "rfaB",
    "positions": [
        [[18.18405709020132, 9.09075541288823, -0.937465553438545], [-9.750912675394435, 7.420315060354796, -16.14982329952681], [8.330053169759784, 1.8009443079896243, 14.065232684663167], [-11.643167542856423, -3.2601130373096154, 6.218306148612035], [-10.650560607557798, -7.400351898746435, -10.004562693422107], [9.634345617941737, -11.851797922802094, 0.9248950327965418], [-15.378034384167107, 11.956583690084665, 2.8891166603896172], [-25.418643257460403, -0.20837221707739922, -8.283110829278822], [24.024013135176098, -2.3885436151518498, 9.152414153147477]]
    ],
    "meshName": "rfaB",
    "excluded_partners_name": [],
    "placeType": "jitter",
    "cutoff_surface": 20.052597999572754,
    "proba_not_binding": 0.5,
    "source": {
        "pdb": "b3628_1_357_2bis_clean",
        "transform": {
            "center": true
        }
    },
    "use_mesh_rb": false,
    "pdb": "b3628_1_357_2bis_clean",
    "useRotAxis": 0
}