{
    "packingMode": "random",
    "partners_position": [],
    "weight": 0.20000000000000001,
    "color": [0.873500139929, 0.181522172033, 0.545316051553],
    "results": [],
    "radii": [[10.0, 10.0, 10.0, 10.0, 10.0, 10.0, 10.0]],
    "cutoff_boundary": null,
    "encapsulatingRadius": 30.9849255472,
    "positions2": null,
    "rejectionThreshold": 30,
    "isAttractor": false,
    "Type": "MultiSphere",
    "orientBiasRotRangeMax": -3.1415926535897931,
    "gradient": "",
    "nbMol": 0,
    "jitterMax": [1.0, 1.0, 1.0],
    "packingPriority": 0,
    "rotAxis": [
        0.0,
        0.0,
        0.0
    ],
    "overwrite_nbMol_value": 0,
    "nbJitter": 5,
    "molarity": 0,
    "useOrientBias": false,
    "rotRange": 6.2831000000000001,
    "coordsystem": "left",
    "meshFile": "tatD_coarse.dae",
    "orientBiasRotRangeMin": -3.1415926535897931,
    "perturbAxisAmplitude": 0.10000000000000001,
    "proba_binding": 0.5,
    "principalVector": [1.0, 0.0, 0.0],
    "offset": [0.0, 0.0, 0.0],
    "properties": {},
    "partners_name": [],
    "name": "tatD",
    "positions": [
        [[11.549031885168178, 10.593295680941171, 1.5977353727130599], [10.683539270265456, -1.2312463466769001, 11.180994006470435], [-5.837101937327534, -3.4511118089915853, -15.569982377356478], [-13.944674548753493, 4.081465942200451, -1.4498952870271127], [8.765488498895213, -8.686830009199664, -6.541331316687236], [-2.883941951548557, 8.100261185355038, 12.020085416984069], [-5.300178347122347, -11.413331425108305, 0.9572357765296886]]
    ],
    "meshName": "tatD",
    "excluded_partners_name": [],
    "placeType": "jitter",
    "cutoff_surface": 20.052597999572754,
    "proba_not_binding": 0.5,
    "source": {
        "pdb": "1xwy-A_clean",
        "transform": {
            "center": true
        }
    },
    "use_mesh_rb": false,
    "pdb": "1xwy-A_clean",
    "useRotAxis": 0
}