{
    "packingMode": "random",
    "partners_position": [],
    "weight": 0.20000000000000001,
    "color": [0.0415370395432, 0.243318402912, 0.090536553211],
    "results": [],
    "radii": [[10.0, 10.0, 10.0, 10.0, 10.0, 10.0, 10.0, 10.0, 10.0, 10.0]],
    "cutoff_boundary": null,
    "encapsulatingRadius": 39.0240342216,
    "positions2": null,
    "rejectionThreshold": 30,
    "isAttractor": false,
    "Type": "MultiSphere",
    "orientBiasRotRangeMax": -3.1415926535897931,
    "gradient": "",
    "nbMol": 0,
    "jitterMax": [1.0, 1.0, 1.0],
    "packingPriority": 0,
    "rotAxis": [
        0.0,
        0.0,
        0.0
    ],
    "overwrite_nbMol_value": 0,
    "nbJitter": 5,
    "molarity": 0,
    "useOrientBias": false,
    "rotRange": 6.2831000000000001,
    "coordsystem": "left",
    "meshFile": "waaA_coarse.dae",
    "orientBiasRotRangeMin": -3.1415926535897931,
    "perturbAxisAmplitude": 0.10000000000000001,
    "proba_binding": 0.5,
    "principalVector": [1.0, 0.0, 0.0],
    "offset": [0.0, 0.0, 0.0],
    "properties": {},
    "partners_name": [],
    "name": "waaA",
    "positions": [
        [[0.6611430439759378, 6.626044825824742, -24.16294640978279], [10.102446535519048, -9.516011193683735, -25.724688462856548], [9.379771351890598, -8.238251553348531, -9.8365620784344], [-6.705338124970235, 7.735616355210966, 25.31982853374705], [-5.4255884392011, -10.438816902270595, 18.21335928859561], [5.6021770713951025, 8.554264083345842, 12.79961852762354], [-9.479921676205956, 4.85657302211211, 4.45217592884619], [-3.418109057110544, 14.149752210297242, -11.75679729577977], [-7.536690348723845, -8.03658125413553, -15.112532382311763], [7.360882512212099, -3.003284991940795, 26.473949397332138]]
    ],
    "meshName": "waaA",
    "excluded_partners_name": [],
    "placeType": "jitter",
    "cutoff_surface": 20.052597999572754,
    "proba_not_binding": 0.5,
    "source": {
        "pdb": "b3633_31_414_2xci_clean",
        "transform": {
            "center": true
        }
    },
    "use_mesh_rb": false,
    "pdb": "b3633_31_414_2xci_clean",
    "useRotAxis": 0
}